[
    {
        "title":"Bags",
        "src":"#",
        "content":[
            {
                "title":"Luggage",
                "src":"#"
            },{
                "title":"Boston",
                "src":"#"
            },{
                "title":"Mayfair",
                "src":"#"
            },{
                "title":"Birkin",
                "src":"#"
            },{
                "title":"Monogram Multicolore",
                "src":"#"
            }            
        ],
        "three":[
        {
            "right":
            [
                {
                    "title":"Final Sale",
                    "src":"#",
                    "content":[
                    {
                        "title":"Louis Vuitton",
                        "src":"#"
                    },{
                        "title":"Gucci Handbags",
                        "src":"#"
                    },{
                        "title":"Prada Handbags",
                        "src":"#"
                    },{
                        "title":"Hermes Handbags",
                        "src":"#"
                    },{
                        "title":"Burbbery Handbags",
                        "src":"#"
                    }]   
                }
            ],
            "left":
            [
                {
                    "content":
                    [
                        {
                            "title":"Baltimore Ravens",
                            "src":"#"                  
                        },{
                            "title":" Baffalo Bills",
                            "src":"#"
                        },{
                            "title":"Cincinati Bengals",
                            "src":"#"
                        },{
                            "title":"Cleveland Browns",
                            "src":"#"
                        },{
                            "title":"Denver Broncos",
                            "src":"#"
                        },{
                            "title":"Houston Texans",
                            "src":"#"
                        },{
                            "title":"Indianapolis Colts",
                            "src":"#"
                        },{
                            "title":"Jaguars",
                            "src":"#"
                        },{
                            "title":"Kansaas City Chiefs",
                            "src":"#"
                        },{
                            "title":"Miami Dolphins",
                            "src":"#"
                        },{
                            "title":"New England Patriots",
                            "src":"#"
                        },{
                            "title":"New York Jets",
                            "src":"#"
                        },{
                            "title":"Oakland Ralders",
                            "src":"#"
                        },{
                            "title":"Pittsburgh Steerlers",
                            "src":"#"
                        },{
                            "title":"Altanas Falcons",
                            "src":"#"
                        },{
                            "title":"Carolina Panthers",
                            "src":"#"
                        },{
                            "title":"Chicago Bears",
                            "src":"#"
                        },{
                            "title":"Dallars Colboys",
                            "src":"#"
                        },{
                            "title":"Detroit Lions",
                            "src":"#"
                        },{
                            "title":"Green Bay Packers",
                            "src":"#"
                        },{
                            "title":"Minnesota Vikings",
                            "src":"#"
                        },{
                            "title":"New Orleans Saints",
                            "src":"#"
                        },{
                            "title":"New York Giants",
                            "src":"#"
                        },{
                            "title":"Philadelphia Eagles",
                            "src":"#"
                        },{
                            "title":"San Francisco 49ers",
                            "src":"#"
                        },{
                            "title":"St. Louis Rams",
                            "src":"#"
                        },{
                            "title":"Washington Redskins",
                            "src":"#"
                        },{
                            "title":"Seattle Seahawks",
                            "src":"#"
                        }
                    ]
                }               
            ]
        }]
    },   
    {
        "title":"Jerseys",
        "src":"#",
        "content":
        [
            {
                "title":"Rolex",
                "src":"#"
            },{
                "title":"Omega",
                "src":"#"
            },{
                "title":"Franck Muller",
                "src":"#"
            },{
                "title":"Cartler",
                "src":"#"
            },{
                "title":"Jacob&co",
                "src":"#"
            },{
                "title":"Armani",
                "src":"#"
            }             
        ],
        "three":[
        {
            "right":
            [
                {
                    "title":"Final Sale",
                    "src":"#",
                    "content":[
                    {
                        "title":"Louis Vuitton",
                        "src":"#"
                    },{
                        "title":"Gucci Handbags",
                        "src":"#"
                    },{
                        "title":"Prada Handbags",
                        "src":"#"
                    },{
                        "title":"Hermes Handbags",
                        "src":"#"
                    },{
                        "title":"Burbbery Handbags",
                        "src":"#"
                    }]   
                }
            ],
            "left":
            [
                {
                    "title":"NFL",
                    "content":
                    [
                        {
                            "title":"Baltimore Ravens",
                            "src":"#"                  
                        },{
                            "title":" Baffalo Bills",
                            "src":"#"
                        },{
                            "title":"Cincinati Bengals",
                            "src":"#"
                        },{
                            "title":"Cleveland Browns",
                            "src":"#"
                        },{
                            "title":"Denver Broncos",
                            "src":"#"
                        },{
                            "title":"Houston Texans",
                            "src":"#"
                        },{
                            "title":"Indianapolis Colts",
                            "src":"#"
                        },{
                            "title":"Jaguars",
                            "src":"#"
                        },{
                            "title":"Kansaas City Chiefs",
                            "src":"#"
                        },{
                            "title":"Miami Dolphins",
                            "src":"#"
                        },{
                            "title":"New England Patriots",
                            "src":"#"
                        },{
                            "title":"New York Jets",
                            "src":"#"
                        },{
                            "title":"Oakland Ralders",
                            "src":"#"
                        },{
                            "title":"Pittsburgh Steerlers",
                            "src":"#"
                        },{
                            "title":"Altanas Falcons",
                            "src":"#"
                        },{
                            "title":"Carolina Panthers",
                            "src":"#"
                        },{
                            "title":"Chicago Bears",
                            "src":"#"
                        },{
                            "title":"Dallars Colboys",
                            "src":"#"
                        },{
                            "title":"Detroit Lions",
                            "src":"#"
                        },{
                            "title":"Green Bay Packers",
                            "src":"#"
                        },{
                            "title":"Minnesota Vikings",
                            "src":"#"
                        },{
                            "title":"New Orleans Saints",
                            "src":"#"
                        },{
                            "title":"New York Giants",
                            "src":"#"
                        },{
                            "title":"Philadelphia Eagles",
                            "src":"#"
                        },{
                            "title":"San Francisco 49ers",
                            "src":"#"
                        },{
                            "title":"St. Louis Rams",
                            "src":"#"
                        },{
                            "title":"Washington Redskins",
                            "src":"#"
                        },{
                            "title":"Seattle Seahawks",
                            "src":"#"
                        }
                    ]
                },{
                    "title":"NBA",
                    "content":[
                        {
                            "title":"Eastern Conference",
                            "src":"#"
                        },{
                            "title":"Western Conference",
                            "src":"#"
                        },{
                            "title":"2012 USA Basketball",
                            "src":"#"
                        }
                    ]
                },{
                    "title":"MLB",
                    "content":[
                        {
                            "title":"National League",
                            "src":"#"
                        },{
                            "title":"American League",
                            "src":"#"
                        }
                    ]
                },{
                    "title":"NHL",
                    "content":[
                        {
                            "title":"Eastern Conference",
                            "src":"#"
                        },{
                            "title":"Western Conference",
                            "src":"#"
                        }
                    ]
                }                 
            ]
        }]
    },
    {
        "title":"Shoes",
        "src":"#",
        "content":[
            {
                "title":"Louis Vuitton",
                "src":"#"
            },{
                "title":"Hermes",
                "src":"#"
            },{
                "title":"Bubbery",
                "src":"#"
            },{
                "title":"Bottega Venta",
                "src":"#"
            },{
                "title":"Balenclaga",
                "src":"#"
            }           
        ],
        "three":[
        {
            "right":
            [
                {
                    "title":"Final Sale",
                    "src":"#",
                    "content":[
                    {
                        "title":"Louis Vuitton",
                        "src":"#"
                    },{
                        "title":"Gucci Handbags",
                        "src":"#"
                    },{
                        "title":"Prada Handbags",
                        "src":"#"
                    },{
                        "title":"Hermes Handbags",
                        "src":"#"
                    },{
                        "title":"Burbbery Handbags",
                        "src":"#"
                    }]   
                }
            ],
            "left":
            [
                {
                    "content":
                    [
                        {
                            "title":"Baltimore Ravens",
                            "src":"#"                  
                        },{
                            "title":" Baffalo Bills",
                            "src":"#"
                        },{
                            "title":"Cincinati Bengals",
                            "src":"#"
                        },{
                            "title":"Cleveland Browns",
                            "src":"#"
                        },{
                            "title":"Denver Broncos",
                            "src":"#"
                        },{
                            "title":"Houston Texans",
                            "src":"#"
                        },{
                            "title":"Indianapolis Colts",
                            "src":"#"
                        },{
                            "title":"Jaguars",
                            "src":"#"
                        },{
                            "title":"Kansaas City Chiefs",
                            "src":"#"
                        },{
                            "title":"Miami Dolphins",
                            "src":"#"
                        },{
                            "title":"New England Patriots",
                            "src":"#"
                        },{
                            "title":"New York Jets",
                            "src":"#"
                        },{
                            "title":"Oakland Ralders",
                            "src":"#"
                        },{
                            "title":"Pittsburgh Steerlers",
                            "src":"#"
                        },{
                            "title":"Altanas Falcons",
                            "src":"#"
                        },{
                            "title":"Carolina Panthers",
                            "src":"#"
                        },{
                            "title":"Chicago Bears",
                            "src":"#"
                        },{
                            "title":"Dallars Colboys",
                            "src":"#"
                        },{
                            "title":"Detroit Lions",
                            "src":"#"
                        },{
                            "title":"Green Bay Packers",
                            "src":"#"
                        },{
                            "title":"Minnesota Vikings",
                            "src":"#"
                        },{
                            "title":"New Orleans Saints",
                            "src":"#"
                        },{
                            "title":"New York Giants",
                            "src":"#"
                        },{
                            "title":"Philadelphia Eagles",
                            "src":"#"
                        },{
                            "title":"San Francisco 49ers",
                            "src":"#"
                        },{
                            "title":"St. Louis Rams",
                            "src":"#"
                        },{
                            "title":"Washington Redskins",
                            "src":"#"
                        },{
                            "title":"Seattle Seahawks",
                            "src":"#"
                        }
                    ]
                }              
            ]
        }]
    },
    {
        "title":"Clothes",
        "src":"#",
        "content":[
            {
                "title":"Louis Vuitton",
                "src":"#"
            },{
                "title":"Gucci",
                "src":"#"
            },{
                "title":"Dior",
                "src":"#"
            },{
                "title":"Prada",
                "src":"#"
            },{
                "title":"Fendi",
                "src":"#"
            },{
                "title":"Ferragamo",
                "src":"#"
            }             
        ],
        "three":[
        {
            "right":
            [
                {
                    "title":"Final Sale",
                    "src":"#",
                    "content":[
                    {
                        "title":"Louis Vuitton",
                        "src":"#"
                    },{
                        "title":"Gucci Handbags",
                        "src":"#"
                    },{
                        "title":"Prada Handbags",
                        "src":"#"
                    },{
                        "title":"Hermes Handbags",
                        "src":"#"
                    },{
                        "title":"Burbbery Handbags",
                        "src":"#"
                    }]   
                }
            ],
            "left":
            [
                {
                    "content":
                    [
                        {
                            "title":"Baltimore Ravens",
                            "src":"#"                  
                        },{
                            "title":" Baffalo Bills",
                            "src":"#"
                        },{
                            "title":"Cincinati Bengals",
                            "src":"#"
                        },{
                            "title":"Cleveland Browns",
                            "src":"#"
                        },{
                            "title":"Denver Broncos",
                            "src":"#"
                        },{
                            "title":"Houston Texans",
                            "src":"#"
                        },{
                            "title":"Indianapolis Colts",
                            "src":"#"
                        },{
                            "title":"Jaguars",
                            "src":"#"
                        },{
                            "title":"Kansaas City Chiefs",
                            "src":"#"
                        },{
                            "title":"Miami Dolphins",
                            "src":"#"
                        },{
                            "title":"New England Patriots",
                            "src":"#"
                        },{
                            "title":"New York Jets",
                            "src":"#"
                        },{
                            "title":"Oakland Ralders",
                            "src":"#"
                        },{
                            "title":"Pittsburgh Steerlers",
                            "src":"#"
                        },{
                            "title":"Altanas Falcons",
                            "src":"#"
                        },{
                            "title":"Carolina Panthers",
                            "src":"#"
                        },{
                            "title":"Chicago Bears",
                            "src":"#"
                        },{
                            "title":"Dallars Colboys",
                            "src":"#"
                        },{
                            "title":"Detroit Lions",
                            "src":"#"
                        },{
                            "title":"Green Bay Packers",
                            "src":"#"
                        },{
                            "title":"Minnesota Vikings",
                            "src":"#"
                        },{
                            "title":"New Orleans Saints",
                            "src":"#"
                        },{
                            "title":"New York Giants",
                            "src":"#"
                        },{
                            "title":"Philadelphia Eagles",
                            "src":"#"
                        },{
                            "title":"San Francisco 49ers",
                            "src":"#"
                        },{
                            "title":"St. Louis Rams",
                            "src":"#"
                        },{
                            "title":"Washington Redskins",
                            "src":"#"
                        },{
                            "title":"Seattle Seahawks",
                            "src":"#"
                        }
                    ]
                }               
            ]
        }]
    },
    {
        "title":"Watches",
        "src":"#",
        "content":[
        {
            "title":"Louis Vuitton",
            "src":"#"
        },{
            "title":"Gucci",
            "src":"#"
        },{
            "title":"Dior",
            "src":"#"
        },{
            "title":"Prada",
            "src":"#"
        },{
            "title":"Fendi",
            "src":"#"
        },{
            "title":"Ferragamo",
            "src":"#"
        }             
        ],
        "three":[
        {
            "right":
            [
                {
                    "title":"Final Sale",
                    "src":"#",
                    "content":[
                    {
                        "title":"Louis Vuitton",
                        "src":"#"
                    },{
                        "title":"Gucci Handbags",
                        "src":"#"
                    },{
                        "title":"Prada Handbags",
                        "src":"#"
                    },{
                        "title":"Hermes Handbags",
                        "src":"#"
                    },{
                        "title":"Burbbery Handbags",
                        "src":"#"
                    }]   
                }
            ],
            "left":
            [
                {
                    "content":
                    [
                        {
                            "title":"Baltimore Ravens",
                            "src":"#"                  
                        },{
                            "title":" Baffalo Bills",
                            "src":"#"
                        },{
                            "title":"Cincinati Bengals",
                            "src":"#"
                        },{
                            "title":"Cleveland Browns",
                            "src":"#"
                        },{
                            "title":"Denver Broncos",
                            "src":"#"
                        },{
                            "title":"Houston Texans",
                            "src":"#"
                        },{
                            "title":"Indianapolis Colts",
                            "src":"#"
                        },{
                            "title":"Jaguars",
                            "src":"#"
                        },{
                            "title":"Kansaas City Chiefs",
                            "src":"#"
                        },{
                            "title":"Miami Dolphins",
                            "src":"#"
                        },{
                            "title":"New England Patriots",
                            "src":"#"
                        },{
                            "title":"New York Jets",
                            "src":"#"
                        },{
                            "title":"Oakland Ralders",
                            "src":"#"
                        },{
                            "title":"Pittsburgh Steerlers",
                            "src":"#"
                        },{
                            "title":"Altanas Falcons",
                            "src":"#"
                        },{
                            "title":"Carolina Panthers",
                            "src":"#"
                        },{
                            "title":"Chicago Bears",
                            "src":"#"
                        },{
                            "title":"Dallars Colboys",
                            "src":"#"
                        },{
                            "title":"Detroit Lions",
                            "src":"#"
                        },{
                            "title":"Green Bay Packers",
                            "src":"#"
                        },{
                            "title":"Minnesota Vikings",
                            "src":"#"
                        },{
                            "title":"New Orleans Saints",
                            "src":"#"
                        },{
                            "title":"New York Giants",
                            "src":"#"
                        },{
                            "title":"Philadelphia Eagles",
                            "src":"#"
                        },{
                            "title":"San Francisco 49ers",
                            "src":"#"
                        },{
                            "title":"St. Louis Rams",
                            "src":"#"
                        },{
                            "title":"Washington Redskins",
                            "src":"#"
                        },{
                            "title":"Seattle Seahawks",
                            "src":"#"
                        }
                    ]
                }
                              
            ]
        }]
    },
    {
        "title":"Accessories",
        "src":"#",
        "content":[
        {
            "title":"Louis Vuitton",
            "src":"#"
        },{
            "title":"Gucci",
            "src":"#"
        },{
            "title":"Dior",
            "src":"#"
        },{
            "title":"Prada",
            "src":"#"
        },{
            "title":"Fendi",
            "src":"#"
        },{
            "title":"Ferragamo",
            "src":"#"
        }             
        ],
        "three":[
        {
            "right":
            [
                {
                    "title":"Final Sale",
                    "src":"#",
                    "content":[
                    {
                        "title":"Louis Vuitton",
                        "src":"#"
                    },{
                        "title":"Gucci Handbags",
                        "src":"#"
                    },{
                        "title":"Prada Handbags",
                        "src":"#"
                    },{
                        "title":"Hermes Handbags",
                        "src":"#"
                    },{
                        "title":"Burbbery Handbags",
                        "src":"#"
                    }]   
                }
            ],
            "left":
            [
                {
                    "content":
                    [
                        {
                            "title":"Baltimore Ravens",
                            "src":"#"                  
                        },{
                            "title":" Baffalo Bills",
                            "src":"#"
                        },{
                            "title":"Cincinati Bengals",
                            "src":"#"
                        },{
                            "title":"Cleveland Browns",
                            "src":"#"
                        },{
                            "title":"Denver Broncos",
                            "src":"#"
                        },{
                            "title":"Houston Texans",
                            "src":"#"
                        },{
                            "title":"Indianapolis Colts",
                            "src":"#"
                        },{
                            "title":"Jaguars",
                            "src":"#"
                        },{
                            "title":"Kansaas City Chiefs",
                            "src":"#"
                        },{
                            "title":"Miami Dolphins",
                            "src":"#"
                        },{
                            "title":"New England Patriots",
                            "src":"#"
                        },{
                            "title":"New York Jets",
                            "src":"#"
                        },{
                            "title":"Oakland Ralders",
                            "src":"#"
                        },{
                            "title":"Pittsburgh Steerlers",
                            "src":"#"
                        },{
                            "title":"Altanas Falcons",
                            "src":"#"
                        },{
                            "title":"Carolina Panthers",
                            "src":"#"
                        },{
                            "title":"Chicago Bears",
                            "src":"#"
                        },{
                            "title":"Dallars Colboys",
                            "src":"#"
                        },{
                            "title":"Detroit Lions",
                            "src":"#"
                        },{
                            "title":"Green Bay Packers",
                            "src":"#"
                        },{
                            "title":"Minnesota Vikings",
                            "src":"#"
                        },{
                            "title":"New Orleans Saints",
                            "src":"#"
                        },{
                            "title":"New York Giants",
                            "src":"#"
                        },{
                            "title":"Philadelphia Eagles",
                            "src":"#"
                        },{
                            "title":"San Francisco 49ers",
                            "src":"#"
                        },{
                            "title":"St. Louis Rams",
                            "src":"#"
                        },{
                            "title":"Washington Redskins",
                            "src":"#"
                        },{
                            "title":"Seattle Seahawks",
                            "src":"#"
                        }
                    ]
                }
                              
            ]
        }]
    }  
]